myo_model/__init__.py
myo_model/examples/__init__.py
myo_model/examples/load_model.py
myo_model/examples/load_model_with_markers.py
myo_model/markerset/cmu_markerset.xml
myo_model/markerset/movi_metrabs_markerset.xml
myo_model/myoskeleton/__init__.py
myo_model/myoskeleton/myoskeleton.xml
myo_model/myoskeleton/includes/myoskeleton_assets.xml
myo_model/myoskeleton/includes/myoskeleton_chain.xml
myo_model/myoskeleton/meshes/1mc.stl
myo_model/myoskeleton/meshes/1mc_l.stl
myo_model/myoskeleton/meshes/2distph.stl
myo_model/myoskeleton/meshes/2distph_l.stl
myo_model/myoskeleton/meshes/2mc.stl
myo_model/myoskeleton/meshes/2mc_l.stl
myo_model/myoskeleton/meshes/2midph.stl
myo_model/myoskeleton/meshes/2midph_l.stl
myo_model/myoskeleton/meshes/2proxph.stl
myo_model/myoskeleton/meshes/2proxph_l.stl
myo_model/myoskeleton/meshes/3distph.stl
myo_model/myoskeleton/meshes/3distph_l.stl
myo_model/myoskeleton/meshes/3mc.stl
myo_model/myoskeleton/meshes/3mc_l.stl
myo_model/myoskeleton/meshes/3midph.stl
myo_model/myoskeleton/meshes/3midph_l.stl
myo_model/myoskeleton/meshes/3proxph.stl
myo_model/myoskeleton/meshes/3proxph_l.stl
myo_model/myoskeleton/meshes/4distph.stl
myo_model/myoskeleton/meshes/4distph_l.stl
myo_model/myoskeleton/meshes/4mc.stl
myo_model/myoskeleton/meshes/4mc_l.stl
myo_model/myoskeleton/meshes/4midph.stl
myo_model/myoskeleton/meshes/4midph_l.stl
myo_model/myoskeleton/meshes/4proxph.stl
myo_model/myoskeleton/meshes/4proxph_l.stl
myo_model/myoskeleton/meshes/5distph.stl
myo_model/myoskeleton/meshes/5distph_l.stl
myo_model/myoskeleton/meshes/5mc.stl
myo_model/myoskeleton/meshes/5mc_l.stl
myo_model/myoskeleton/meshes/5midph.stl
myo_model/myoskeleton/meshes/5midph_l.stl
myo_model/myoskeleton/meshes/5proxph.stl
myo_model/myoskeleton/meshes/5proxph_l.stl
myo_model/myoskeleton/meshes/capitate.stl
myo_model/myoskeleton/meshes/capitate_l.stl
myo_model/myoskeleton/meshes/cerv1.stl
myo_model/myoskeleton/meshes/cerv2.stl
myo_model/myoskeleton/meshes/cerv3.stl
myo_model-0.0.0.dist-info/licenses/LICENSE
myo_model-0.0.0.dist-info/METADATA
myo_model-0.0.0.dist-info/WHEEL
myo_model-0.0.0.dist-info/top_level.txt
myo_model-0.0.0.dist-info/RECORD
