Metadata-Version: 2.4
Name: myo_model
Version: 0.0.0
Summary: myo_model is a library of carefully constructed musculoskeletal models.
Author: myolab
Requires-Python: >=3.10
License-File: LICENSE
Requires-Dist: myo_tools
Requires-Dist: mujoco>=3.2.4
Provides-Extra: dev
Requires-Dist: pre-commit; extra == "dev"
Requires-Dist: pytest; extra == "dev"
Requires-Dist: mock; extra == "dev"
Requires-Dist: click; extra == "dev"
Provides-Extra: test
Requires-Dist: pytest; extra == "test"
Requires-Dist: mock; extra == "test"
Requires-Dist: click; extra == "test"
Dynamic: license-file
